pdf_watermark_removal/__init__.py
pdf_watermark_removal/cli.py
pdf_watermark_removal/color_analyzer.py
pdf_watermark_removal/color_selector.py
pdf_watermark_removal/document_classifier.py
pdf_watermark_removal/i18n.py
pdf_watermark_removal/pdf_processor.py
pdf_watermark_removal/stats.py
pdf_watermark_removal/watermark_detector.py
pdf_watermark_removal/watermark_remover.py
pdf_watermark_removal_otsu_inpaint-0.4.1.dist-info/METADATA
pdf_watermark_removal_otsu_inpaint-0.4.1.dist-info/WHEEL
pdf_watermark_removal_otsu_inpaint-0.4.1.dist-info/entry_points.txt
pdf_watermark_removal_otsu_inpaint-0.4.1.dist-info/RECORD
