Metadata-Version: 2.4
Name: pdf-watermark-removal-otsu-inpaint
Version: 0.4.1
Summary: Remove watermarks from PDF using Otsu threshold segmentation and OpenCV inpaint
Author: Tinnci
License: MIT
Keywords: image-processing,inpaint,otsu,pdf,removal,watermark
Classifier: Development Status :: 4 - Beta
Classifier: Intended Audience :: Developers
Classifier: License :: OSI Approved :: MIT License
Classifier: Operating System :: OS Independent
Classifier: Programming Language :: Python :: 3
Classifier: Programming Language :: Python :: 3.8
Classifier: Programming Language :: Python :: 3.9
Classifier: Programming Language :: Python :: 3.10
Classifier: Programming Language :: Python :: 3.11
Classifier: Programming Language :: Python :: 3.12
Classifier: Topic :: Multimedia :: Graphics :: Presentation
Classifier: Topic :: Office/Business
Requires-Python: >=3.8
Requires-Dist: click>=8.0.0
Requires-Dist: numpy>=1.21.0
Requires-Dist: opencv-python>=4.8.0
Requires-Dist: pillow>=9.0.0
Requires-Dist: pymupdf>=1.23.0
Requires-Dist: pypdf>=3.0.0
Requires-Dist: rich>=13.0.0
Provides-Extra: dev
Requires-Dist: black>=23.0.0; extra == 'dev'
Requires-Dist: pytest>=7.0.0; extra == 'dev'
Requires-Dist: ruff>=0.1.0; extra == 'dev'
